microsoft/__init__.py
microsoft/opentelemetry/__init__.py
microsoft/opentelemetry/exporter/__init__.py
microsoft/opentelemetry/exporter/azuremonitor/__init__.py
microsoft/opentelemetry/exporter/azuremonitor/_version.py
microsoft/opentelemetry/exporter/azuremonitor/options.py
microsoft/opentelemetry/exporter/azuremonitor/storage.py
microsoft/opentelemetry/exporter/azuremonitor/utils.py
microsoft/opentelemetry/exporter/azuremonitor/_generated/__init__.py
microsoft/opentelemetry/exporter/azuremonitor/_generated/_azure_monitor_client.py
microsoft/opentelemetry/exporter/azuremonitor/_generated/_configuration.py
microsoft/opentelemetry/exporter/azuremonitor/_generated/aio/__init__.py
microsoft/opentelemetry/exporter/azuremonitor/_generated/aio/_azure_monitor_client_async.py
microsoft/opentelemetry/exporter/azuremonitor/_generated/aio/_configuration_async.py
microsoft/opentelemetry/exporter/azuremonitor/_generated/aio/operations_async/__init__.py
microsoft/opentelemetry/exporter/azuremonitor/_generated/aio/operations_async/_azure_monitor_client_operations_async.py
microsoft/opentelemetry/exporter/azuremonitor/_generated/models/__init__.py
microsoft/opentelemetry/exporter/azuremonitor/_generated/models/_azure_monitor_client_enums.py
microsoft/opentelemetry/exporter/azuremonitor/_generated/models/_models.py
microsoft/opentelemetry/exporter/azuremonitor/_generated/models/_models_py3.py
microsoft/opentelemetry/exporter/azuremonitor/_generated/operations/__init__.py
microsoft/opentelemetry/exporter/azuremonitor/_generated/operations/_azure_monitor_client_operations.py
microsoft/opentelemetry/exporter/azuremonitor/export/__init__.py
microsoft/opentelemetry/exporter/azuremonitor/export/trace/__init__.py
microsoft_opentelemetry_exporter_azuremonitor-1.0.0b1.dist-info/LICENSE.txt
microsoft_opentelemetry_exporter_azuremonitor-1.0.0b1.dist-info/METADATA
microsoft_opentelemetry_exporter_azuremonitor-1.0.0b1.dist-info/WHEEL
microsoft_opentelemetry_exporter_azuremonitor-1.0.0b1.dist-info/top_level.txt
microsoft_opentelemetry_exporter_azuremonitor-1.0.0b1.dist-info/RECORD
