Metadata-Version: 2.1
Name: microsoft-opentelemetry-exporter-azuremonitor
Version: 1.0.0b1
Summary: Microsoft Azure Monitor Opentelemetry Exporter Client Library for Python
Home-page: https://github.com/Azure/azure-sdk-for-python/tree/master/sdk/monitor/microsoft-opentelemetry-exporter-azuremonitor
Author: Microsoft Corporation
Author-email: ascl@microsoft.com
License: MIT License
Platform: UNKNOWN
Classifier: Development Status :: 4 - Beta
Classifier: Programming Language :: Python
Classifier: Programming Language :: Python :: 3
Classifier: Programming Language :: Python :: 3.5
Classifier: Programming Language :: Python :: 3.6
Classifier: Programming Language :: Python :: 3.7
Classifier: Programming Language :: Python :: 3.8
Classifier: Programming Language :: Python :: 3.9
Classifier: License :: OSI Approved :: MIT License
Requires-Python: >=3.5.0
Requires-Dist: azure-core (<2.0.0,>=1.6.0)
Requires-Dist: msrest (>=0.6.10)
Requires-Dist: opentelemetry-api (==0.15b0)
Requires-Dist: opentelemetry-sdk (==0.15b0)
